odoo/addons/account_fiscal_year/README.rst
odoo/addons/account_fiscal_year/__init__.py
odoo/addons/account_fiscal_year/__manifest__.py
odoo/addons/account_fiscal_year/data/date_range_type.xml
odoo/addons/account_fiscal_year/i18n/account_fiscal_year.pot
odoo/addons/account_fiscal_year/i18n/fr.po
odoo/addons/account_fiscal_year/i18n/it.po
odoo/addons/account_fiscal_year/i18n/nl.po
odoo/addons/account_fiscal_year/readme/CONTRIBUTORS.rst
odoo/addons/account_fiscal_year/readme/DESCRIPTION.rst
odoo/addons/account_fiscal_year/static/description/icon.png
odoo/addons/account_fiscal_year/static/description/index.html
odoo/addons/account_fiscal_year/views/account_views.xml
odoo13_addon_account_fiscal_year-13.0.1.0.1.dev11.dist-info/METADATA
odoo13_addon_account_fiscal_year-13.0.1.0.1.dev11.dist-info/WHEEL
odoo13_addon_account_fiscal_year-13.0.1.0.1.dev11.dist-info/top_level.txt
odoo13_addon_account_fiscal_year-13.0.1.0.1.dev11.dist-info/RECORD
