Metadata-Version: 2.1
Name: odoo13-addon-account_fiscal_year
Version: 13.0.1.0.1.dev11
Summary: Create a menu for Account Fiscal Year
Home-page: https://github.com/OCA/account-financial-tools
Author: Agile Business Group, Camptocamp SA, Odoo Community Association (OCA)
Author-email: support@odoo-community.org
License: AGPL-3
Classifier: Programming Language :: Python
Classifier: Framework :: Odoo
Classifier: Framework :: Odoo :: 13.0
Classifier: License :: OSI Approved :: GNU Affero General Public License v3
Classifier: Development Status :: 4 - Beta
Requires-Python: >=3.5
Requires-Dist: odoo13-addon-date-range
Requires-Dist: odoo<13.1dev,>=13.0a
